[{"word": "helyettesít", "class": "word"}, {"word": "aláíkos", "class": "nonword"},{"word": "hirtelen", "class": "word"}, {"word": "váratlanul", "class": "word"},{"word": "kapénia", "class": "nonword"}, {"word": "fájdonom", "class": "nonword"},{"word": "inspagál", "class": "nonword"}, {"word": "dopül", "class": "nonword"},{"word": "sár", "class": "word"}, {"word": "heti", "class": "word"},{"word": "korona", "class": "word"}, {"word": "trón", "class": "word"},{"word": "rómeó", "class": "word"}, {"word": "tartalom", "class": "word"},{"word": "koeterencia", "class": "nonword"}, {"word": "tenisz", "class": "word"},{"word": "árverés", "class": "word"}, {"word": "bíum", "class": "nonword"},{"word": "költségvetés", "class": "word"}, {"word": "finanszírozás", "class": "word"},{"word": "hős", "class": "word"}, {"word": "megmentő", "class": "word"},{"word": "kisóget", "class": "nonword"}, {"word": "utób", "class": "nonword"},{"word": "siker", "class": "word"}, {"word": "kudarc", "class": "word"},{"word": "teék", "class": "nonword"}, {"word": "kolmpetne", "class": "nonword"},{"word": "ún", "class": "nonword"}, {"word": "eszköz", "class": "word"},{"word": "kilométer", "class": "word"}, {"word": "méter", "class": "word"},{"word": "tajtés", "class": "nonword"}, {"word": "ködenség", "class": "nonword"},{"word": "tényező", "class": "word"}, {"word": "junior", "class": "word"},{"word": "kövelje", "class": "nonword"}, {"word": "kimelaszt", "class": "nonword"},{"word": "visszaverődés", "class": "word"}, {"word": "elékanti", "class": "nonword"},{"word": "kig", "class": "nonword"}, {"word": "üzenet", "class": "word"},{"word": "mada", "class": "nonword"}, {"word": "szőkész", "class": "nonword"},{"word": "maralan", "class": "nonword"}, {"word": "finalizírozás", "class": "nonword"},{"word": "egyszerűen", "class": "word"}, {"word": "fogás", "class": "word"},{"word": "coányítás", "class": "nonword"}, {"word": "kifejez", "class": "word"},{"word": "szokatton", "class": "nonword"}, {"word": "fomes", "class": "nonword"},{"word": "átok", "class": "word"}, {"word": "boszorkány", "class": "word"},{"word": "szikla", "class": "word"}, {"word": "kő", "class": "word"},{"word": "internet", "class": "word"}, {"word": "gyerock", "class": "nonword"},{"word": "költő", "class": "word"}, {"word": "író", "class": "word"},{"word": "már", "class": "word"}, {"word": "választás", "class": "word"},{"word": "élő", "class": "word"}, {"word": "helikosher", "class": "nonword"},{"word": "feszújtség", "class": "nonword"}, {"word": "barátságos", "class": "word"},{"word": "esküszik", "class": "word"}, {"word": "szósz", "class": "word"},{"word": "folytassa", "class": "word"}, {"word": "folytatni", "class": "word"},{"word": "szendvics", "class": "word"}, {"word": "serit", "class": "nonword"},{"word": "rendar", "class": "nonword"}, {"word": "neter", "class": "nonword"},{"word": "bajnok", "class": "word"}, {"word": "harcos", "class": "word"},{"word": "hétfő", "class": "word"}, {"word": "kedd", "class": "word"},{"word": "rtő", "class": "nonword"}, {"word": "csvei", "class": "nonword"},{"word": "környeont", "class": "nonword"}, {"word": "pénzpnyi", "class": "nonword"},{"word": "lomisság", "class": "nonword"}, {"word": "tnány", "class": "nonword"},{"word": "csont", "class": "word"}, {"word": "koponya", "class": "word"},{"word": "whisky", "class": "word"}, {"word": "jeézz", "class": "nonword"},{"word": "desszert", "class": "word"}, {"word": "tulajdonos", "class": "word"},{"word": "akintáska", "class": "nonword"}, {"word": "hegy", "class": "word"},{"word": "véltny", "class": "nonword"}, {"word": "készöd", "class": "nonword"},{"word": "visszapérődés", "class": "nonword"}, {"word": "kenzőp", "class": "nonword"},{"word": "forrtá", "class": "nonword"}, {"word": "előadás", "class": "word"},{"word": "megpróbál", "class": "word"}, {"word": "alír", "class": "nonword"}]
