[{"word": "stot", "class": "nonword"}, {"word": "politics", "class": "word"},{"word": "yko", "class": "nonword"}, {"word": "limouworm", "class": "nonword"},{"word": "person", "class": "word"}, {"word": "fog", "class": "word"},{"word": "skinnical", "class": "nonword"}, {"word": "lockelty", "class": "nonword"},{"word": "pocket", "class": "word"}, {"word": "sculpegy", "class": "nonword"},{"word": "curse", "class": "word"}, {"word": "cargo", "class": "word"},{"word": "forchae", "class": "nonword"}, {"word": "chire", "class": "nonword"},{"word": "relative", "class": "word"}, {"word": "pain", "class": "word"},{"word": "ambucombe", "class": "nonword"}, {"word": "inforerin", "class": "nonword"},{"word": "kilo", "class": "word"}, {"word": "intimate", "class": "word"},{"word": "evidates", "class": "nonword"}, {"word": "blin", "class": "nonword"},{"word": "spab", "class": "nonword"}, {"word": "arand", "class": "nonword"},{"word": "saturday", "class": "word"}, {"word": "sunday", "class": "word"},{"word": "geview", "class": "nonword"}, {"word": "girls", "class": "word"},{"word": "licit", "class": "nonword"}, {"word": "imporcians", "class": "nonword"},{"word": "special", "class": "word"}, {"word": "prodong", "class": "nonword"},{"word": "candimock", "class": "nonword"}, {"word": "allim", "class": "nonword"},{"word": "girl", "class": "word"}, {"word": "analysis", "class": "word"},{"word": "silent", "class": "word"}, {"word": "nucliff", "class": "nonword"},{"word": "exciting", "class": "word"}, {"word": "interesting", "class": "word"},{"word": "useless", "class": "word"}, {"word": "esmaud", "class": "nonword"},{"word": "exlonging", "class": "nonword"}, {"word": "pidas", "class": "nonword"},{"word": "wheakey", "class": "nonword"}, {"word": "vikyo", "class": "nonword"},{"word": "drem", "class": "nonword"}, {"word": "minus", "class": "word"},{"word": "colmuch", "class": "nonword"}, {"word": "income", "class": "word"},{"word": "illutors", "class": "nonword"}, {"word": "gate", "class": "word"},{"word": "food", "class": "word"}, {"word": "meal", "class": "word"},{"word": "decent", "class": "word"}, {"word": "honest", "class": "word"},{"word": "pacific", "class": "word"}, {"word": "atlantic", "class": "word"},{"word": "porise", "class": "nonword"}, {"word": "heca", "class": "nonword"},{"word": "reproved", "class": "nonword"}, {"word": "lonely", "class": "word"},{"word": "worm", "class": "word"}, {"word": "wedding", "class": "word"},{"word": "hanging", "class": "word"}, {"word": "entrepreneur", "class": "word"},{"word": "flag", "class": "word"}, {"word": "assassin", "class": "word"},{"word": "double", "class": "word"}, {"word": "triple", "class": "word"},{"word": "sengal", "class": "nonword"}, {"word": "kingnar", "class": "nonword"},{"word": "war", "class": "word"}, {"word": "battle", "class": "word"},{"word": "natuquently", "class": "nonword"}, {"word": "reses", "class": "nonword"},{"word": "intung", "class": "nonword"}, {"word": "asfice", "class": "nonword"},{"word": "task", "class": "word"}, {"word": "educapable", "class": "nonword"},{"word": "invasion", "class": "word"}, {"word": "frighten", "class": "word"},{"word": "climb", "class": "word"}, {"word": "opment", "class": "nonword"},{"word": "chack", "class": "nonword"}, {"word": "basi", "class": "nonword"},{"word": "health", "class": "word"}, {"word": "education", "class": "word"},{"word": "warning", "class": "word"}, {"word": "audience", "class": "word"},{"word": "pump", "class": "word"}, {"word": "assist", "class": "word"},{"word": "polcle", "class": "nonword"}, {"word": "sals", "class": "nonword"},{"word": "gormic", "class": "nonword"}, {"word": "aliwell", "class": "nonword"},{"word": "oglent", "class": "nonword"}, {"word": "lonu", "class": "nonword"},{"word": "fisively", "class": "nonword"}, {"word": "tomato", "class": "word"}]
