[{"word": "폼에", "class": "nonword"}, {"word": "까의먹", "class": "nonword"},{"word": "논평", "class": "word"}, {"word": "형제", "class": "word"},{"word": "구석", "class": "word"}, {"word": "결심", "class": "word"},{"word": "가엔", "class": "nonword"}, {"word": "짐자승", "class": "nonword"},{"word": "호위", "class": "word"}, {"word": "게이", "class": "word"},{"word": "끼워 넣다", "class": "word"}, {"word": "죽은", "class": "word"},{"word": "배이타", "class": "nonword"}, {"word": "네묻", "class": "nonword"},{"word": "크루", "class": "word"}, {"word": "배", "class": "word"},{"word": "혼돈", "class": "word"}, {"word": "짱이", "class": "nonword"},{"word": "떠나스밑둔", "class": "nonword"}, {"word": "움이", "class": "nonword"},{"word": "샌디", "class": "nonword"}, {"word": "정치가", "class": "word"},{"word": "프란의", "class": "nonword"}, {"word": "햇밍다", "class": "nonword"},{"word": "나역", "class": "nonword"}, {"word": "비밀클린", "class": "nonword"},{"word": "졸업장", "class": "word"}, {"word": "기랑", "class": "nonword"},{"word": "화", "class": "word"}, {"word": "임대", "class": "word"},{"word": "기다좋게", "class": "nonword"}, {"word": "선수", "class": "word"},{"word": "장했을", "class": "nonword"}, {"word": "사기", "class": "word"},{"word": "전문인", "class": "word"}, {"word": "금성", "class": "word"},{"word": "배야다하", "class": "nonword"}, {"word": "만나다", "class": "word"},{"word": "유행의", "class": "word"}, {"word": "녹음", "class": "word"},{"word": "캐하", "class": "nonword"}, {"word": "애프", "class": "nonword"},{"word": "담요", "class": "word"}, {"word": "정의", "class": "word"},{"word": "변론받", "class": "nonword"}, {"word": "임에", "class": "nonword"},{"word": "아프리카", "class": "word"}, {"word": "옵션", "class": "word"},{"word": "빗애", "class": "nonword"}, {"word": "라팀", "class": "nonword"},{"word": "프는", "class": "nonword"}, {"word": "서으", "class": "nonword"},{"word": "경험", "class": "word"}, {"word": "묶다", "class": "word"},{"word": "수프", "class": "word"}, {"word": "락은", "class": "nonword"},{"word": "배배파다", "class": "nonword"}, {"word": "세차수 없는", "class": "nonword"},{"word": "정량", "class": "word"}, {"word": "씨토", "class": "nonword"},{"word": "적", "class": "word"}, {"word": "폭발", "class": "word"},{"word": "의콥", "class": "nonword"}, {"word": "산", "class": "word"},{"word": "도로", "class": "word"}, {"word": "한둣", "class": "nonword"},{"word": "용서", "class": "word"}, {"word": "가치로즈는", "class": "nonword"},{"word": "산업", "class": "word"}, {"word": "받았한", "class": "nonword"},{"word": "린제", "class": "nonword"}, {"word": "별탕듯한", "class": "nonword"},{"word": "아래", "class": "word"}, {"word": "유명한", "class": "word"},{"word": "프니", "class": "nonword"}, {"word": "툼은", "class": "nonword"},{"word": "겠구", "class": "nonword"}, {"word": "원동", "class": "nonword"},{"word": "러씨", "class": "nonword"}, {"word": "놔뒀", "class": "nonword"},{"word": "무모한", "class": "word"}, {"word": "에스이", "class": "nonword"},{"word": "떨어지다", "class": "word"}, {"word": "음악가", "class": "word"},{"word": "천", "class": "word"}, {"word": "백", "class": "word"},{"word": "타브", "class": "nonword"}, {"word": "나운", "class": "nonword"},{"word": "마스턴", "class": "nonword"}, {"word": "미알", "class": "nonword"},{"word": "레즈상승", "class": "nonword"}, {"word": "그핫듯한", "class": "nonword"},{"word": "로한다", "class": "nonword"}, {"word": "테론", "class": "nonword"},{"word": "골프", "class": "word"}, {"word": "태양의", "class": "word"},{"word": "하늘의 뜻", "class": "word"}, {"word": "베이컨", "class": "word"},{"word": "타야궁", "class": "nonword"}, {"word": "누가팅", "class": "nonword"}]
