[{"word": "дейтесьвать", "class": "nonword"}, {"word": "спасиствель", "class": "nonword"},{"word": "буквально", "class": "word"}, {"word": "гошань", "class": "nonword"},{"word": "рубьемка", "class": "nonword"}, {"word": "флирный", "class": "nonword"},{"word": "родственник", "class": "word"}, {"word": "кузен", "class": "word"},{"word": "кретный", "class": "nonword"}, {"word": "процокоз", "class": "nonword"},{"word": "джентливый", "class": "nonword"}, {"word": "рыним", "class": "nonword"},{"word": "бумага", "class": "word"}, {"word": "учёрия", "class": "nonword"},{"word": "описывать", "class": "word"}, {"word": "выражать", "class": "word"},{"word": "вобратжение", "class": "nonword"}, {"word": "богалетый", "class": "nonword"},{"word": "очарование", "class": "word"}, {"word": "красота", "class": "word"},{"word": "гранп", "class": "nonword"}, {"word": "кусок", "class": "word"},{"word": "пират", "class": "word"}, {"word": "моряк", "class": "word"},{"word": "шпион", "class": "word"}, {"word": "полдень", "class": "word"},{"word": "ролние", "class": "nonword"}, {"word": "фаса", "class": "nonword"},{"word": "нелепый", "class": "word"}, {"word": "абсурдный", "class": "word"},{"word": "вадность", "class": "nonword"}, {"word": "должливый", "class": "nonword"},{"word": "карьера", "class": "word"}, {"word": "репутация", "class": "word"},{"word": "перетц", "class": "nonword"}, {"word": "сумма", "class": "word"},{"word": "баяншой", "class": "nonword"}, {"word": "стека", "class": "nonword"},{"word": "невозможный", "class": "word"}, {"word": "легкий", "class": "word"},{"word": "беспокойгно", "class": "nonword"}, {"word": "закломный", "class": "nonword"},{"word": "вшина", "class": "nonword"}, {"word": "ла кравило", "class": "nonword"},{"word": "справедливый", "class": "word"}, {"word": "патереск", "class": "nonword"},{"word": "человид", "class": "nonword"}, {"word": "арендовать", "class": "word"},{"word": "сокровище", "class": "word"}, {"word": "военно-морской", "class": "word"},{"word": "медведь", "class": "word"}, {"word": "присяга", "class": "word"},{"word": "экспертиза", "class": "word"}, {"word": "проверка", "class": "word"},{"word": "победа", "class": "word"}, {"word": "поражение", "class": "word"},{"word": "кодентка", "class": "nonword"}, {"word": "котофе", "class": "nonword"},{"word": "сентябрь", "class": "word"}, {"word": "легенда", "class": "word"},{"word": "промышленность", "class": "word"}, {"word": "окончательный", "class": "word"},{"word": "безумие", "class": "word"}, {"word": "странера", "class": "nonword"},{"word": "ночь", "class": "word"}, {"word": "символ", "class": "word"},{"word": "королева", "class": "word"}, {"word": "король", "class": "word"},{"word": "зеленый", "class": "word"}, {"word": "оранжевый", "class": "word"},{"word": "подростковый", "class": "word"}, {"word": "краснадо", "class": "nonword"},{"word": "благодарный", "class": "word"}, {"word": "параграф", "class": "word"},{"word": "зверь", "class": "word"}, {"word": "нос", "class": "word"},{"word": "бангульский", "class": "nonword"}, {"word": "ватсон", "class": "word"},{"word": "кавалерия", "class": "word"}, {"word": "акцент", "class": "word"},{"word": "дом", "class": "word"}, {"word": "продолскимать", "class": "nonword"},{"word": "родклассник", "class": "nonword"}, {"word": "до свиддресс", "class": "nonword"},{"word": "индивид", "class": "word"}, {"word": "человек", "class": "word"},{"word": "ботимист", "class": "nonword"}, {"word": "заем", "class": "word"},{"word": "коричневый", "class": "word"}, {"word": "фантазия", "class": "word"},{"word": "мецейс", "class": "nonword"}, {"word": "бакрый", "class": "nonword"},{"word": "название", "class": "word"}, {"word": "теет", "class": "nonword"},{"word": "свидетель", "class": "word"}, {"word": "показание", "class": "word"},{"word": "вселенная", "class": "word"}, {"word": "свисток", "class": "word"},{"word": "довольно", "class": "word"}, {"word": "пошелец", "class": "nonword"}]
