[{"word": "떠나스밑둔", "class": "nonword"}, {"word": "움이", "class": "nonword"},{"word": "납치범", "class": "word"}, {"word": "몸값", "class": "word"},{"word": "히만", "class": "nonword"}, {"word": "브에", "class": "nonword"},{"word": "반사", "class": "word"}, {"word": "뒤쫓다", "class": "word"},{"word": "장이다", "class": "nonword"}, {"word": "극을", "class": "nonword"},{"word": "신선한", "class": "word"}, {"word": "폭풍", "class": "word"},{"word": "반어", "class": "word"}, {"word": "너이자", "class": "nonword"},{"word": "자부심", "class": "word"}, {"word": "설치", "class": "word"},{"word": "감자", "class": "word"}, {"word": "토마토", "class": "word"},{"word": "디저트", "class": "word"}, {"word": "머저", "class": "nonword"},{"word": "방패", "class": "word"}, {"word": "불공정", "class": "word"},{"word": "재퍼", "class": "nonword"}, {"word": "꾼을", "class": "nonword"},{"word": "비싼", "class": "word"}, {"word": "짐자승", "class": "nonword"},{"word": "고통", "class": "word"}, {"word": "고문", "class": "word"},{"word": "할수있게하다", "class": "word"}, {"word": "하냐 조달", "class": "nonword"},{"word": "자비한", "class": "word"}, {"word": "저대", "class": "nonword"},{"word": "로로", "class": "nonword"}, {"word": "저기", "class": "word"},{"word": "인형", "class": "word"}, {"word": "오넬", "class": "nonword"},{"word": "금지된", "class": "word"}, {"word": "재결", "class": "nonword"},{"word": "단어", "class": "word"}, {"word": "문장", "class": "word"},{"word": "락파", "class": "nonword"}, {"word": "문주기", "class": "nonword"},{"word": "완쾌하다", "class": "word"}, {"word": "갈테", "class": "nonword"},{"word": "논평", "class": "word"}, {"word": "성명", "class": "word"},{"word": "의지할 곳이 없는", "class": "word"}, {"word": "강엽병", "class": "nonword"},{"word": "해변", "class": "word"}, {"word": "기계식", "class": "word"},{"word": "시인", "class": "word"}, {"word": "수술", "class": "word"},{"word": "바늘", "class": "word"}, {"word": "마이티의", "class": "nonword"},{"word": "려끌언", "class": "nonword"}, {"word": "슨네", "class": "nonword"},{"word": "어락명해", "class": "nonword"}, {"word": "지명이", "class": "nonword"},{"word": "졸업장", "class": "word"}, {"word": "권한", "class": "word"},{"word": "죽음", "class": "word"}, {"word": "즌이", "class": "nonword"},{"word": "병기고", "class": "word"}, {"word": "무기고", "class": "word"},{"word": "리해", "class": "nonword"}, {"word": "업통", "class": "nonword"},{"word": "알았어", "class": "word"}, {"word": "수도원", "class": "word"},{"word": "프란의", "class": "nonword"}, {"word": "햇밍다", "class": "nonword"},{"word": "극도로", "class": "word"}, {"word": "매우", "class": "word"},{"word": "펙스", "class": "nonword"}, {"word": "짓다", "class": "word"},{"word": "우투하다", "class": "nonword"}, {"word": "수꼼", "class": "nonword"},{"word": "석탄", "class": "word"}, {"word": "사진라나가", "class": "nonword"},{"word": "연예인", "class": "word"}, {"word": "노프", "class": "nonword"},{"word": "보지", "class": "nonword"}, {"word": "무너더를", "class": "nonword"},{"word": "티쿠스", "class": "nonword"}, {"word": "산소", "class": "word"},{"word": "탕바", "class": "nonword"}, {"word": "중단운", "class": "nonword"},{"word": "병원", "class": "word"}, {"word": "진료소", "class": "word"},{"word": "잡담", "class": "word"}, {"word": "스캔들", "class": "word"},{"word": "렌을", "class": "nonword"}, {"word": "입구", "class": "word"},{"word": "제어", "class": "word"}, {"word": "반듯", "class": "nonword"},{"word": "라식이", "class": "nonword"}, {"word": "합법적 인", "class": "word"},{"word": "들으하다", "class": "nonword"}, {"word": "그기색", "class": "nonword"},{"word": "핑튜미", "class": "nonword"}, {"word": "가치로즈는", "class": "nonword"}]
