[{"word": "brundmaddel", "class": "nonword"}, {"word": "serveerster", "class": "word"},{"word": "tank", "class": "word"}, {"word": "motor", "class": "word"},{"word": "kewoesnateriool", "class": "nonword"}, {"word": "regevech", "class": "nonword"},{"word": "persoon", "class": "word"}, {"word": "zon", "class": "word"},{"word": "kwantiteit", "class": "word"}, {"word": "mooi", "class": "word"},{"word": "tegennuud", "class": "nonword"}, {"word": "doneska", "class": "nonword"},{"word": "fabriek", "class": "word"}, {"word": "ochtend", "class": "word"},{"word": "regionaal", "class": "word"}, {"word": "taart", "class": "word"},{"word": "constraf", "class": "nonword"}, {"word": "spruuk", "class": "nonword"},{"word": "modder", "class": "word"}, {"word": "vermogen", "class": "word"},{"word": "kras", "class": "word"}, {"word": "kneuzing", "class": "word"},{"word": "viley", "class": "nonword"}, {"word": "ticon", "class": "nonword"},{"word": "kloor", "class": "nonword"}, {"word": "dote", "class": "nonword"},{"word": "kidparren", "class": "nonword"}, {"word": "climis", "class": "nonword"},{"word": "vergeten", "class": "word"}, {"word": "onthouden", "class": "word"},{"word": "alleen", "class": "word"}, {"word": "heno", "class": "nonword"},{"word": "klimware", "class": "nonword"}, {"word": "gy", "class": "nonword"},{"word": "leatisch", "class": "nonword"}, {"word": "globaal", "class": "word"},{"word": "drankje", "class": "word"}, {"word": "oefening", "class": "word"},{"word": "saard", "class": "nonword"}, {"word": "onzund", "class": "nonword"},{"word": "lamp", "class": "word"}, {"word": "kaars", "class": "word"},{"word": "begeleiden", "class": "word"}, {"word": "weom", "class": "nonword"},{"word": "strucondergang", "class": "nonword"}, {"word": "literamaakt", "class": "nonword"},{"word": "absoluut", "class": "word"}, {"word": "volledig", "class": "word"},{"word": "verven", "class": "word"}, {"word": "volduk", "class": "nonword"},{"word": "kamp", "class": "word"}, {"word": "bier", "class": "word"},{"word": "feaak", "class": "nonword"}, {"word": "benier", "class": "nonword"},{"word": "uitzonderlijk", "class": "word"}, {"word": "triew", "class": "nonword"},{"word": "raron", "class": "nonword"}, {"word": "spette", "class": "nonword"},{"word": "norlist", "class": "nonword"}, {"word": "gabets", "class": "nonword"},{"word": "uitleg", "class": "word"}, {"word": "aannemelijk", "class": "word"},{"word": "nep", "class": "word"}, {"word": "exfe", "class": "nonword"},{"word": "sestemde", "class": "nonword"}, {"word": "grin", "class": "nonword"},{"word": "terster", "class": "nonword"}, {"word": "posinaas", "class": "nonword"},{"word": "redesche", "class": "nonword"}, {"word": "ofn", "class": "nonword"},{"word": "warmte", "class": "word"}, {"word": "temperatuur", "class": "word"},{"word": "blikuur", "class": "nonword"}, {"word": "zelfdig", "class": "nonword"},{"word": "spalen", "class": "nonword"}, {"word": "antbeelden", "class": "nonword"},{"word": "ulk", "class": "nonword"}, {"word": "weom", "class": "nonword"},{"word": "on sief spokkan", "class": "nonword"}, {"word": "kanvoel", "class": "nonword"},{"word": "land", "class": "word"}, {"word": "enck", "class": "nonword"},{"word": "nalis", "class": "nonword"}, {"word": "demoncrieftie", "class": "nonword"},{"word": "zatermijn", "class": "nonword"}, {"word": "spoc", "class": "nonword"},{"word": "conoverle", "class": "nonword"}, {"word": "handeving", "class": "nonword"},{"word": "sterkte", "class": "word"}, {"word": "koffie", "class": "word"},{"word": "karof", "class": "nonword"}, {"word": "egoiachtig", "class": "nonword"},{"word": "muis", "class": "word"}, {"word": "fotograaf", "class": "word"},{"word": "arselend", "class": "nonword"}, {"word": "lavong", "class": "nonword"},{"word": "fallun", "class": "nonword"}, {"word": "guvens", "class": "nonword"},{"word": "indruk", "class": "word"}, {"word": "gevoel", "class": "word"}]
