[{"word": "قرتل", "class": "nonword"}, {"word": "يكل", "class": "nonword"},{"word": "دسته", "class": "word"}, {"word": "تخیل", "class": "word"},{"word": "دوربین", "class": "word"}, {"word": "ساختن", "class": "word"},{"word": "بیمارستان", "class": "word"}, {"word": "درمانگاه", "class": "word"},{"word": "سخن", "class": "word"}, {"word": "پُر", "class": "word"},{"word": "ترذیر", "class": "nonword"}, {"word": "وزاب", "class": "nonword"},{"word": "نانیخ", "class": "nonword"}, {"word": "لیبرهن", "class": "nonword"},{"word": "دارچین", "class": "word"}, {"word": "ورود", "class": "word"},{"word": "نگبرق", "class": "nonword"}, {"word": "جزه", "class": "nonword"},{"word": "تجربه", "class": "word"}, {"word": "گره زدن", "class": "word"},{"word": "دراما", "class": "word"}, {"word": "هذیان", "class": "word"},{"word": "سود", "class": "word"}, {"word": "پرواز", "class": "word"},{"word": "کورب", "class": "nonword"}, {"word": "نيور", "class": "nonword"},{"word": "آتش", "class": "word"}, {"word": "فسی", "class": "nonword"},{"word": "آهسته. تدرتری", "class": "nonword"}, {"word": "شکلات", "class": "word"},{"word": "گويشکنید", "class": "nonword"}, {"word": "عرشه", "class": "word"},{"word": "رولاانه", "class": "nonword"}, {"word": "ویروس اِچ آی وی", "class": "word"},{"word": "گفتگو", "class": "word"}, {"word": "بحث", "class": "word"},{"word": "آبجو", "class": "word"}, {"word": "دور", "class": "word"},{"word": "فنفان", "class": "nonword"}, {"word": "جمظره", "class": "nonword"},{"word": "لایس", "class": "nonword"}, {"word": "کلاسیک", "class": "word"},{"word": "يق", "class": "nonword"}, {"word": "بابهی", "class": "nonword"},{"word": "تور", "class": "word"}, {"word": "کنسرت", "class": "word"},{"word": "گاز", "class": "word"}, {"word": "سوخت", "class": "word"},{"word": "فاطيه", "class": "nonword"}, {"word": "گلیاک", "class": "nonword"},{"word": "تووب", "class": "nonword"}, {"word": "لباس فرم", "class": "word"},{"word": "قحدن", "class": "nonword"}, {"word": "ازدواج", "class": "word"},{"word": "آنژيلانزا", "class": "nonword"}, {"word": "مردم", "class": "word"},{"word": "دکنده", "class": "nonword"}, {"word": "تحصیلات", "class": "word"},{"word": "محئه", "class": "nonword"}, {"word": "ونهام", "class": "nonword"},{"word": "زنتگر", "class": "nonword"}, {"word": "هااسیک", "class": "nonword"},{"word": "ویجای", "class": "nonword"}, {"word": "كاته", "class": "nonword"},{"word": "امروز", "class": "word"}, {"word": "دیروز", "class": "word"},{"word": "توصیلمکردن", "class": "nonword"}, {"word": "کازبون", "class": "nonword"},{"word": "دسته", "class": "word"}, {"word": "گروه", "class": "word"},{"word": "نخوبان", "class": "nonword"}, {"word": "صندلی", "class": "word"},{"word": "ظریف", "class": "word"}, {"word": "حساس", "class": "word"},{"word": "قبلاً", "class": "word"}, {"word": "ردنده", "class": "nonword"},{"word": "مسنلر", "class": "nonword"}, {"word": "رخزاوده", "class": "nonword"},{"word": "مغيره", "class": "nonword"}, {"word": "دکنه", "class": "nonword"},{"word": "وجتان", "class": "nonword"}, {"word": "قااط", "class": "nonword"},{"word": "ساختن", "class": "word"}, {"word": "تولید کردن", "class": "word"},{"word": "كرمن", "class": "nonword"}, {"word": "غلرت", "class": "nonword"},{"word": "آواه", "class": "nonword"}, {"word": "عمل جرپزي", "class": "nonword"},{"word": "تتری", "class": "nonword"}, {"word": "دلسوزی", "class": "word"},{"word": "ظرصي", "class": "nonword"}, {"word": "برو", "class": "word"},{"word": "تاارکی", "class": "nonword"}, {"word": "تدریس کردن", "class": "word"},{"word": "شرارت", "class": "word"}, {"word": "بی‌رحمی", "class": "word"},{"word": "دریانت", "class": "nonword"}, {"word": "نیروفشدریایی", "class": "nonword"},{"word": "يرک", "class": "nonword"}, {"word": "کموننیت", "class": "nonword"}]
